prophecy/__init__.py
prophecy/random_data_creator.py
prophecy/config/__init__.py
prophecy/config/config_base.py
prophecy/config/utils.py
prophecy/dbxsless/__init__.py
prophecy/dbxsless/dbx_serverless_helper.py
prophecy/dbxsless/requirements.dbxserverless_sandbox.txt
prophecy/executionmetrics/__init__.py
prophecy/executionmetrics/execution_metrics_handler.py
prophecy/executionmetrics/in_memory_store.py
prophecy/executionmetrics/logging_spark_session.py
prophecy/executionmetrics/models.py
prophecy/executionmetrics/package.py
prophecy/executionmetrics/workflow_parser.py
prophecy/executionmetrics/zip_file.py
prophecy/executionmetrics/componentruns/__init__.py
prophecy/executionmetrics/componentruns/component_run_service.py
prophecy/executionmetrics/componentruns/component_runs_dao.py
prophecy/executionmetrics/evolutions/__init__.py
prophecy/executionmetrics/evolutions/delta_metrics_storage_initializer.py
prophecy/executionmetrics/evolutions/hive_parquet_storage_initializer.py
prophecy/executionmetrics/evolutions/metrics_storage_initializer.py
prophecy/executionmetrics/evolutions/models.py
prophecy/executionmetrics/evolutions/package.py
prophecy/executionmetrics/interims/__init__.py
prophecy/executionmetrics/interims/delta_interims.py
prophecy/executionmetrics/interims/hive_parquet_interims.py
prophecy/executionmetrics/interims/interims_table.py
prophecy/executionmetrics/pipelineruns/__init__.py
prophecy/executionmetrics/pipelineruns/pipeline_run_service.py
prophecy/executionmetrics/pipelineruns/pipeline_runs_dao.py
prophecy/executionmetrics/schemas/__init__.py
prophecy/executionmetrics/schemas/em.py
prophecy/executionmetrics/schemas/external.py
prophecy/executionmetrics/utils/__init__.py
prophecy/executionmetrics/utils/common.py
prophecy/executionmetrics/utils/constants.py
prophecy/executionmetrics/utils/external.py
prophecy/executionmetrics/utils/interim_store.py
prophecy/jsonrpc/__init__.py
prophecy/jsonrpc/models.py
prophecy/libs/__init__.py
prophecy_libs-2.1.5.dist-info/LICENSE
prophecy_libs-2.1.5.dist-info/METADATA
prophecy_libs-2.1.5.dist-info/WHEEL
prophecy_libs-2.1.5.dist-info/top_level.txt
prophecy_libs-2.1.5.dist-info/RECORD
