Metadata-Version: 2.1
Name: prophecy-libs
Version: 2.1.5
Summary: Helper library for prophecy generated code
Home-page: https://github.com/SimpleDataLabsInc/prophecy-python-libs
Author: UNKNOWN
Author-email: UNKNOWN
License: GPL-3.0
Keywords: python,prophecy
Platform: UNKNOWN
Requires-Dist: hvac (==2.3.0)
Requires-Dist: msgspec (>=0.18.6)
Requires-Dist: pyhocon (>=0.3.59)
Requires-Dist: requests (>=2.10.0)
Requires-Dist: zstandard (>=0.23.0)
